taiga_tasks/__init__.py
taiga_tasks/main.py
taiga_tasks/api/__init__.py
taiga_tasks/api/client.py
taiga_tasks/cli/__init__.py
taiga_tasks/cli/commands.py
taiga_tasks/config/__init__.py
taiga_tasks/config/manager.py
taiga_tasks/config/settings.py
taiga_tasks/display/__init__.py
taiga_tasks/display/formatters.py
taiga_tasks-0.2.0.dist-info/METADATA
taiga_tasks-0.2.0.dist-info/WHEEL
taiga_tasks-0.2.0.dist-info/entry_points.txt
taiga_tasks-0.2.0.dist-info/RECORD
