Metadata-Version: 2.4
Name: taiga-tasks
Version: 0.2.0
Summary: A CLI tool to display Taiga tasks assigned to you.
Project-URL: Homepage, https://github.com/codewithemd/taiga-tasks
Author-email: Emad Rad <codewithemd@gmail.com>
License: MIT
Classifier: License :: OSI Approved :: MIT License
Classifier: Operating System :: OS Independent
Classifier: Programming Language :: Python :: 3
Requires-Python: >=3.7
Requires-Dist: python-dotenv==1.1.1
Requires-Dist: python-taiga==1.3.0
Requires-Dist: rich==14.1.0
Provides-Extra: dev
Requires-Dist: ruff==0.12.8; extra == 'dev'
